py_scrapi/__init__.py
py_scrapi/datatrails_droid_engine.py
py_scrapi/datatrails_engine.py
py_scrapi/datatrails_events_engine.py
py_scrapi/null_engine.py
py_scrapi/py_scrapi.py
py_scrapi/scrapi_engine.py
py_scrapi/scrapi_exception.py
py_scrapi-0.1.3.dist-info/LICENSE
py_scrapi-0.1.3.dist-info/METADATA
py_scrapi-0.1.3.dist-info/WHEEL
py_scrapi-0.1.3.dist-info/top_level.txt
py_scrapi-0.1.3.dist-info/RECORD
