Metadata-Version: 2.2
Name: py_scrapi
Version: 0.1.3
Summary: Python wrapper for IETF SCITT reference API (SCRAPI)
Home-page: https://github.com/scitt-community/py-scrapi
Author: JAG-UK
License: MIT
Classifier: Programming Language :: Python :: 3
Classifier: License :: OSI Approved :: MIT License
Classifier: Operating System :: OS Independent
Requires-Python: >=3.6
License-File: LICENSE
Requires-Dist: cbor2
Requires-Dist: ecdsa==0.18.0
Requires-Dist: pycose==1.0.1
Requires-Dist: rfc9290
Dynamic: author
Dynamic: classifier
Dynamic: description
Dynamic: description-content-type
Dynamic: home-page
Dynamic: license
Dynamic: requires-dist
Dynamic: requires-python
Dynamic: summary
